Metadata-Version: 1.0
Name: tst2021-distribution
Version: 1.0
Summary: Gaussian and Binomial distribution
Home-page: UNKNOWN
Author: UNKNOWN
Author-email: UNKNOWN
License: UNKNOWN
Platform: UNKNOWN
